jsonvault/__init__.py
jsonvault/db_structs.py
jsonvault/io.py
jsonvault-0.1.0.dist-info/METADATA
jsonvault-0.1.0.dist-info/WHEEL
jsonvault-0.1.0.dist-info/entry_points.txt
jsonvault-0.1.0.dist-info/RECORD
