Metadata-Version: 2.4
Name: jsonvault
Version: 0.1.0
Summary: DB with JSON files
Author-email: Aero <aerocyberdev@proton.me>
Requires-Python: >=3.13
